py_handles/__init__.py
py_handles/extras.py
py_handles/integer_handles.py
py_handles-0.0.1.dist-info/METADATA
py_handles-0.0.1.dist-info/WHEEL
py_handles-0.0.1.dist-info/top_level.txt
py_handles-0.0.1.dist-info/RECORD
