Metadata-Version: 2.1
Name: py-handles
Version: 0.0.1
Summary: Simple manipulative python package.
Author: MITdude
License: MIT
Keywords: mainpulative,python handles
